{"0": {"Open": 67.45, "High": 68.95, "Low": 67.45, "Close": 68.6, "Change": null, "Traded Volume": 23870.0, "Turnover": 1636088.25, "Last Price of the Day": null, "Daily Traded Units": null, "Daily Turnover": null}, "1": {"Open": 68.45, "High": 68.5, "Low": 67.65, "Close": 67.95, "Change": null, "Traded Volume": 39471.0, "Turnover": 2682215.25, "Last Price of the Day": null, "Daily Traded Units": null, "Daily Turnover": null}, "2": {"Open": 67.75, "High": 68.3, "Low": 66.95, "Close": 68.3, "Change": null, "Traded Volume": 52741.0, "Turnover": 3581800.0, "Last Price of the Day": null, "Daily Traded Units": null, "Daily Turnover": null}, "3": {"Open": 68.5, "High": 69.2, "Low": 68.25, "Close": 69.0, "Change": null, "Traded Volume": 47538.0, "Turnover": 3269830.0, "Last Price of the Day": null, "Daily Traded Units": null, "Daily Turnover": null}, "4": {"Open": 68.25, "High": 68.5, "Low": 67.15, "Close": 67.35, "Change": null, "Traded Volume": 43904.0, "Turnover": 2973259.5, "Last Price of the Day": null, "Daily Traded Units": null, "Daily Turnover": null}, "5": {"Open": 68.0, "High": 69.05, "Low": 68.0, "Close": 68.85, "Change": null, "Traded Volume": 35940.0, "Turnover": 2468447.25, "Last Price of the Day": null, "Daily Traded Units": null, "Daily Turnover": null}, "6": {"Open": 69.45, "High": 69.6, "Low": 68.1, "Close": 68.1, "Change": null, "Traded Volume": 39719.0, "Turnover": 2724097.0, "Last Price of the Day": null, "Daily Traded Units": null, "Daily Turnover": null}, "7": {"Open": 68.45, "High": 68.5, "Low": 67.8, "Close": 67.8, "Change": null, "Traded Volume": 23582.0, "Turnover": 1602158.25, "Last Price of the Day": null, "Daily Traded Units": null, "Daily Turnover": null}, "8": {"Open": 68.15, "High": 68.25, "Low": 67.45, "Close": 68.05, "Change": null, "Traded Volume": 25914.0, "Turnover": 1758296.13, "Last Price of the Day": null, "Daily Traded Units": null, "Daily Turnover": null}, "9": {"Open": 68.55, "High": 68.55, "Low": 67.6, "Close": 68.1, "Change": null, "Traded Volume": 38052.0, "Turnover": 2586690.25, "Last Price of the Day": null, "Daily Traded Units": null, "Daily Turnover": null}, "10": {"Open": 68.25, "High": 69.2, "Low": 67.75, "Close": 68.75, "Change": null, "Traded Volume": 43954.0, "Turnover": 3018370.75, "Last Price of the Day": null, "Daily Traded Units": null, "Daily Turnover": null}, "11": {"Open": 68.5, "High": 69.55, "Low": 68.5, "Close": 68.8, "Change": null, "Traded Volume": 34346.0, "Turnover": 2364996.75, "Last Price of the Day": null, "Daily Traded Units": null, "Daily Turnover": null}, "12": {"Open": 68.75, "High": 71.1, "Low": 68.75, "Close": 70.85, "Change": null, "Traded Volume": 39797.0, "Turnover": 2798559.5, "Last Price of the Day": null, "Daily Traded Units": null, "Daily Turnover": null}, "13": {"Open": 70.45, "High": 71.15, "Low": 69.2, "Close": 70.3, "Change": null, "Traded Volume": 41250.0, "Turnover": 2898012.25, "Last Price of the Day": null, "Daily Traded Units": null, "Daily Turnover": null}, "14": {"Open": 69.0, "High": 70.4, "Low": 69.0, "Close": 69.5, "Change": null, "Traded Volume": 38829.0, "Turnover": 2704647.5, "Last Price of the Day": null, "Daily Traded Units": null, "Daily Turnover": null}, "15": {"Open": 69.65, "High": 69.65, "Low": 68.7, "Close": 69.3, "Change": null, "Traded Volume": 77231.0, "Turnover": 5337096.0, "Last Price of the Day": null, "Daily Traded Units": null, "Daily Turnover": null}, "16": {"Open": 73.0, "High": 75.5, "Low": 71.15, "Close": 71.65, "Change": null, "Traded Volume": 129683.0, "Turnover": 9475439.0, "Last Price of the Day": null, "Daily Traded Units": null, "Daily Turnover": null}, "17": {"Open": 71.0, "High": 71.0, "Low": 68.55, "Close": 68.7, "Change": null, "Traded Volume": 90262.0, "Turnover": 6249682.0, "Last Price of the Day": null, "Daily Traded Units": null, "Daily Turnover": null}, "18": {"Open": 69.4, "High": 69.4, "Low": 66.1, "Close": 68.7, "Change": null, "Traded Volume": 63199.0, "Turnover": 4296660.5, "Last Price of the Day": null, "Daily Traded Units": null, "Daily Turnover": null}, "19": {"Open": 68.75, "High": 70.35, "Low": 68.3, "Close": 70.0, "Change": null, "Traded Volume": 53987.0, "Turnover": 3755821.5, "Last Price of the Day": null, "Daily Traded Units": null, "Daily Turnover": null}, "20": {"Open": 70.05, "High": 70.2, "Low": 68.35, "Close": 69.6, "Change": null, "Traded Volume": 41893.0, "Turnover": 2907458.5, "Last Price of the Day": null, "Daily Traded Units": null, "Daily Turnover": null}, "21": {"Open": 69.5, "High": 70.4, "Low": 68.5, "Close": 68.55, "Change": null, "Traded Volume": 56152.0, "Turnover": 3874603.0, "Last Price of the Day": null, "Daily Traded Units": null, "Daily Turnover": null}, "22": {"Open": 68.95, "High": 70.35, "Low": 68.4, "Close": 70.35, "Change": null, "Traded Volume": 28250.0, "Turnover": 1968193.0, "Last Price of the Day": null, "Daily Traded Units": null, "Daily Turnover": null}, "23": {"Open": 70.45, "High": 72.0, "Low": 69.95, "Close": 71.95, "Change": null, "Traded Volume": 33585.0, "Turnover": 2404119.75, "Last Price of the Day": null, "Daily Traded Units": null, "Daily Turnover": null}, "24": {"Open": 73.45, "High": 73.85, "Low": 72.85, "Close": 73.4, "Change": null, "Traded Volume": 78349.0, "Turnover": 5734070.5, "Last Price of the Day": null, "Daily Traded Units": null, "Daily Turnover": null}, "25": {"Open": 73.4, "High": 73.95, "Low": 71.4, "Close": 71.4, "Change": null, "Traded Volume": 47378.0, "Turnover": 3414139.5, "Last Price of the Day": null, "Daily Traded Units": null, "Daily Turnover": null}, "26": {"Open": 71.05, "High": 71.05, "Low": 69.85, "Close": 70.05, "Change": null, "Traded Volume": 37648.0, "Turnover": 2648013.0, "Last Price of the Day": null, "Daily Traded Units": null, "Daily Turnover": null}, "27": {"Open": 70.0, "High": 71.2, "Low": 69.25, "Close": 70.65, "Change": null, "Traded Volume": 45131.0, "Turnover": 3183857.25, "Last Price of the Day": null, "Daily Traded Units": null, "Daily Turnover": null}, "28": {"Open": 70.5, "High": 72.1, "Low": 70.5, "Close": 72.05, "Change": null, "Traded Volume": 42339.0, "Turnover": 3035677.75, "Last Price of the Day": null, "Daily Traded Units": null, "Daily Turnover": null}, "29": {"Open": 72.4, "High": 73.0, "Low": 72.15, "Close": 72.4, "Change": null, "Traded Volume": 45284.0, "Turnover": 3282391.5, "Last Price of the Day": null, "Daily Traded Units": null, "Daily Turnover": null}, "30": {"Open": 72.05, "High": 72.4, "Low": 70.7, "Close": 71.35, "Change": null, "Traded Volume": 38928.0, "Turnover": 2780072.25, "Last Price of the Day": null, "Daily Traded Units": null, "Daily Turnover": null}, "31": {"Open": 70.95, "High": 71.95, "Low": 70.95, "Close": 71.2, "Change": null, "Traded Volume": 22599.0, "Turnover": 1613812.75, "Last Price of the Day": null, "Daily Traded Units": null, "Daily Turnover": null}, "32": {"Open": 71.8, "High": 72.0, "Low": 71.25, "Close": 71.8, "Change": null, "Traded Volume": 27921.0, "Turnover": 2001777.0, "Last Price of the Day": null, "Daily Traded Units": null, "Daily Turnover": null}, "33": {"Open": 70.0, "High": 70.6, "Low": 68.55, "Close": 69.9, "Change": null, "Traded Volume": 69682.0, "Turnover": 4853060.5, "Last Price of the Day": null, "Daily Traded Units": null, "Daily Turnover": null}, "34": {"Open": 69.85, "High": 70.5, "Low": 69.35, "Close": 70.3, "Change": null, "Traded Volume": 69456.0, "Turnover": 4872190.5, "Last Price of the Day": null, "Daily Traded Units": null, "Daily Turnover": null}, "35": {"Open": 68.9, "High": 70.3, "Low": 67.05, "Close": 70.0, "Change": null, "Traded Volume": 134689.0, "Turnover": 9302365.0, "Last Price of the Day": null, "Daily Traded Units": null, "Daily Turnover": null}, "36": {"Open": 69.6, "High": 69.6, "Low": 63.1, "Close": 63.6, "Change": null, "Traded Volume": 255403.0, "Turnover": 16474957.0, "Last Price of the Day": null, "Daily Traded Units": null, "Daily Turnover": null}, "37": {"Open": 61.55, "High": 61.55, "Low": 59.9, "Close": 60.5, "Change": null, "Traded Volume": 110255.0, "Turnover": 6676504.0, "Last Price of the Day": null, "Daily Traded Units": null, "Daily Turnover": null}, "38": {"Open": 60.95, "High": 61.15, "Low": 59.0, "Close": 59.3, "Change": null, "Traded Volume": 89743.0, "Turnover": 5377476.15, "Last Price of the Day": null, "Daily Traded Units": null, "Daily Turnover": null}, "39": {"Open": 58.8, "High": 60.55, "Low": 57.3, "Close": 60.4, "Change": null, "Traded Volume": 124694.0, "Turnover": 7374931.5, "Last Price of the Day": null, "Daily Traded Units": null, "Daily Turnover": null}, "40": {"Open": 59.75, "High": 60.1, "Low": 57.45, "Close": 58.25, "Change": null, "Traded Volume": 100009.0, "Turnover": 5845974.4, "Last Price of the Day": null, "Daily Traded Units": null, "Daily Turnover": null}, "41": {"Open": 57.0, "High": 57.15, "Low": 54.8, "Close": 56.6, "Change": null, "Traded Volume": 133236.0, "Turnover": 7481611.65, "Last Price of the Day": null, "Daily Traded Units": null, "Daily Turnover": null}, "42": {"Open": 56.95, "High": 57.95, "Low": 55.35, "Close": 56.45, "Change": null, "Traded Volume": 97251.0, "Turnover": 5487715.2, "Last Price of the Day": null, "Daily Traded Units": null, "Daily Turnover": null}, "43": {"Open": 57.8, "High": 59.1, "Low": 57.15, "Close": 57.25, "Change": null, "Traded Volume": 76366.0, "Turnover": 4434283.05, "Last Price of the Day": null, "Daily Traded Units": null, "Daily Turnover": null}, "44": {"Open": 58.0, "High": 58.1, "Low": 56.75, "Close": 56.8, "Change": null, "Traded Volume": 79841.0, "Turnover": 4572747.1, "Last Price of the Day": null, "Daily Traded Units": null, "Daily Turnover": null}, "45": {"Open": 57.65, "High": 58.2, "Low": 54.85, "Close": 55.25, "Change": null, "Traded Volume": 99165.0, "Turnover": 5511995.65, "Last Price of the Day": null, "Daily Traded Units": null, "Daily Turnover": null}, "46": {"Open": 53.45, "High": 54.7, "Low": 53.0, "Close": 54.3, "Change": null, "Traded Volume": 91370.0, "Turnover": 4916762.3, "Last Price of the Day": null, "Daily Traded Units": null, "Daily Turnover": null}, "47": {"Open": 50.8, "High": 52.7, "Low": 50.1, "Close": 50.9, "Change": null, "Traded Volume": 188165.0, "Turnover": 9677131.45, "Last Price of the Day": null, "Daily Traded Units": null, "Daily Turnover": null}, "48": {"Open": 51.65, "High": 53.35, "Low": 50.4, "Close": 50.9, "Change": null, "Traded Volume": 204859.0, "Turnover": 10585705.3, "Last Price of the Day": null, "Daily Traded Units": null, "Daily Turnover": null}, "49": {"Open": 52.35, "High": 52.4, "Low": 50.5, "Close": 50.8, "Change": null, "Traded Volume": 123339.0, "Turnover": 6315106.25, "Last Price of the Day": null, "Daily Traded Units": null, "Daily Turnover": null}, "50": {"Open": 48.16, "High": 48.34, "Low": 46.3, "Close": 46.3, "Change": null, "Traded Volume": 178078.0, "Turnover": 8405411.02, "Last Price of the Day": null, "Daily Traded Units": null, "Daily Turnover": null}, "51": {"Open": 49.08, "High": 50.25, "Low": 46.0, "Close": 47.4, "Change": null, "Traded Volume": 165287.0, "Turnover": 7949183.03, "Last Price of the Day": null, "Daily Traded Units": null, "Daily Turnover": null}, "52": {"Open": 45.0, "High": 46.86, "Low": 42.68, "Close": 46.4, "Change": null, "Traded Volume": 175210.0, "Turnover": 7819590.3, "Last Price of the Day": null, "Daily Traded Units": null, "Daily Turnover": null}, "53": {"Open": 47.4, "High": 48.82, "Low": 43.7, "Close": 48.58, "Change": null, "Traded Volume": 127230.0, "Turnover": 5938645.52, "Last Price of the Day": null, "Daily Traded Units": null, "Daily Turnover": null}, "54": {"Open": 47.74, "High": 48.0, "Low": 44.04, "Close": 46.2, "Change": null, "Traded Volume": 111289.0, "Turnover": 5096240.6, "Last Price of the Day": null, "Daily Traded Units": null, "Daily Turnover": null}, "55": {"Open": 46.22, "High": 46.36, "Low": 42.1, "Close": 46.0, "Change": null, "Traded Volume": 137978.0, "Turnover": 6152935.14, "Last Price of the Day": null, "Daily Traded Units": null, "Daily Turnover": null}, "56": {"Open": 47.02, "High": 48.62, "Low": 43.86, "Close": 44.32, "Change": null, "Traded Volume": 152068.0, "Turnover": 6965123.46, "Last Price of the Day": null, "Daily Traded Units": null, "Daily Turnover": null}, "57": {"Open": 43.7, "High": 44.18, "Low": 41.92, "Close": 42.92, "Change": null, "Traded Volume": 82907.0, "Turnover": 3551416.84, "Last Price of the Day": null, "Daily Traded Units": null, "Daily Turnover": null}, "58": {"Open": 44.98, "High": 46.04, "Low": 43.8, "Close": 46.04, "Change": null, "Traded Volume": 57959.0, "Turnover": 2611264.4, "Last Price of the Day": null, "Daily Traded Units": null, "Daily Turnover": null}, "59": {"Open": 47.78, "High": 48.52, "Low": 44.7, "Close": 48.38, "Change": null, "Traded Volume": 105219.0, "Turnover": 4898619.3, "Last Price of the Day": null, "Daily Traded Units": null, "Daily Turnover": null}, "60": {"Open": 49.0, "High": 50.0, "Low": 46.56, "Close": 48.86, "Change": null, "Traded Volume": 52715.0, "Turnover": 2532721.14, "Last Price of the Day": null, "Daily Traded Units": null, "Daily Turnover": null}, "61": {"Open": 48.8, "High": 48.8, "Low": 46.44, "Close": 47.9, "Change": null, "Traded Volume": 42745.0, "Turnover": 2041496.9, "Last Price of the Day": null, "Daily Traded Units": null, "Daily Turnover": null}, "62": {"Open": 48.74, "High": 48.78, "Low": 45.12, "Close": 48.78, "Change": null, "Traded Volume": 48669.0, "Turnover": 2323600.1, "Last Price of the Day": null, "Daily Traded Units": null, "Daily Turnover": null}, "63": {"Open": 49.12, "High": 50.55, "Low": 47.92, "Close": 48.78, "Change": null, "Traded Volume": 55245.0, "Turnover": 2700466.56, "Last Price of the Day": null, "Daily Traded Units": null, "Daily Turnover": null}, "64": {"Open": 48.0, "High": 48.4, "Low": 46.02, "Close": 47.3, "Change": null, "Traded Volume": 48836.0, "Turnover": 2307565.92, "Last Price of the Day": null, "Daily Traded Units": null, "Daily Turnover": null}, "65": {"Open": 46.5, "High": 47.82, "Low": 45.88, "Close": 47.24, "Change": null, "Traded Volume": 44279.0, "Turnover": 2078723.86, "Last Price of the Day": null, "Daily Traded Units": null, "Daily Turnover": null}, "66": {"Open": 47.72, "High": 47.76, "Low": 46.36, "Close": 46.36, "Change": null, "Traded Volume": 24611.0, "Turnover": 1151363.82, "Last Price of the Day": null, "Daily Traded Units": null, "Daily Turnover": null}, "67": {"Open": 48.0, "High": 50.1, "Low": 47.74, "Close": 49.38, "Change": null, "Traded Volume": 64148.0, "Turnover": 3164615.2, "Last Price of the Day": null, "Daily Traded Units": null, "Daily Turnover": null}, "68": {"Open": 51.2, "High": 52.75, "Low": 50.85, "Close": 52.4, "Change": null, "Traded Volume": 65828.0, "Turnover": 3419980.0, "Last Price of the Day": null, "Daily Traded Units": null, "Daily Turnover": null}, "69": {"Open": 51.5, "High": 52.5, "Low": 50.6, "Close": 51.2, "Change": null, "Traded Volume": 28656.0, "Turnover": 1471828.7, "Last Price of the Day": null, "Daily Traded Units": null, "Daily Turnover": null}, "70": {"Open": 51.5, "High": 53.45, "Low": 51.15, "Close": 52.9, "Change": null, "Traded Volume": 32836.0, "Turnover": 1728851.05, "Last Price of the Day": null, "Daily Traded Units": null, "Daily Turnover": null}, "71": {"Open": 53.8, "High": 54.5, "Low": 51.85, "Close": 52.65, "Change": null, "Traded Volume": 55158.0, "Turnover": 2914233.75, "Last Price of the Day": null, "Daily Traded Units": null, "Daily Turnover": null}, "72": {"Open": 52.55, "High": 52.55, "Low": 50.1, "Close": 50.2, "Change": null, "Traded Volume": 28527.0, "Turnover": 1446101.95, "Last Price of the Day": null, "Daily Traded Units": null, "Daily Turnover": null}, "73": {"Open": 50.55, "High": 51.8, "Low": 50.15, "Close": 51.0, "Change": null, "Traded Volume": 32144.0, "Turnover": 1642277.45, "Last Price of the Day": null, "Daily Traded Units": null, "Daily Turnover": null}, "74": {"Open": 52.7, "High": 53.5, "Low": 52.1, "Close": 53.35, "Change": null, "Traded Volume": 35165.0, "Turnover": 1864673.2, "Last Price of the Day": null, "Daily Traded Units": null, "Daily Turnover": null}, "75": {"Open": 53.9, "High": 56.6, "Low": 53.25, "Close": 55.65, "Change": null, "Traded Volume": 72187.0, "Turnover": 3981175.85, "Last Price of the Day": null, "Daily Traded Units": null, "Daily Turnover": null}, "76": {"Open": 54.55, "High": 54.85, "Low": 52.85, "Close": 54.1, "Change": null, "Traded Volume": 54294.0, "Turnover": 2918240.35, "Last Price of the Day": null, "Daily Traded Units": null, "Daily Turnover": null}, "77": {"Open": 54.2, "High": 55.35, "Low": 53.3, "Close": 54.45, "Change": null, "Traded Volume": 38062.0, "Turnover": 2071475.55, "Last Price of the Day": null, "Daily Traded Units": null, "Daily Turnover": null}, "78": {"Open": 54.7, "High": 56.05, "Low": 54.7, "Close": 55.45, "Change": null, "Traded Volume": 36200.0, "Turnover": 2008075.75, "Last Price of the Day": null, "Daily Traded Units": null, "Daily Turnover": null}, "79": {"Open": 54.1, "High": 55.0, "Low": 53.4, "Close": 53.5, "Change": null, "Traded Volume": 17980.0, "Turnover": 970149.65, "Last Price of the Day": null, "Daily Traded Units": null, "Daily Turnover": null}, "80": {"Open": 53.25, "High": 55.05, "Low": 53.25, "Close": 54.9, "Change": null, "Traded Volume": 12552.0, "Turnover": 684927.65, "Last Price of the Day": null, "Daily Traded Units": null, "Daily Turnover": null}, "81": {"Open": 55.8, "High": 55.85, "Low": 54.5, "Close": 55.2, "Change": null, "Traded Volume": 23230.0, "Turnover": 1284094.55, "Last Price of the Day": null, "Daily Traded Units": null, "Daily Turnover": null}, "82": {"Open": 55.3, "High": 59.9, "Low": 54.85, "Close": 59.6, "Change": null, "Traded Volume": 71798.0, "Turnover": 4164863.95, "Last Price of the Day": null, "Daily Traded Units": null, "Daily Turnover": null}, "83": {"Open": 58.6, "High": 59.4, "Low": 54.9, "Close": 55.05, "Change": null, "Traded Volume": 117431.0, "Turnover": 6558869.7, "Last Price of the Day": null, "Daily Traded Units": null, "Daily Turnover": null}, "84": {"Open": 53.85, "High": 54.6, "Low": 51.7, "Close": 53.4, "Change": null, "Traded Volume": 130999.0, "Turnover": 6990675.95, "Last Price of the Day": null, "Daily Traded Units": null, "Daily Turnover": null}, "85": {"Open": 54.5, "High": 55.4, "Low": 53.4, "Close": 54.9, "Change": null, "Traded Volume": 42130.0, "Turnover": 2298970.5, "Last Price of the Day": null, "Daily Traded Units": null, "Daily Turnover": null}, "86": {"Open": 54.4, "High": 55.15, "Low": 54.0, "Close": 54.3, "Change": null, "Traded Volume": 47038.0, "Turnover": 2564979.55, "Last Price of the Day": null, "Daily Traded Units": null, "Daily Turnover": null}, "87": {"Open": 54.05, "High": 55.95, "Low": 53.75, "Close": 54.95, "Change": null, "Traded Volume": 32998.0, "Turnover": 1812895.2, "Last Price of the Day": null, "Daily Traded Units": null, "Daily Turnover": null}, "88": {"Open": 54.65, "High": 56.95, "Low": 54.45, "Close": 56.55, "Change": null, "Traded Volume": 29815.0, "Turnover": 1676019.15, "Last Price of the Day": null, "Daily Traded Units": null, "Daily Turnover": null}}