{"0": {"Open": 12.22, "High": 12.53, "Low": 12.2, "Close": 12.38, "Change": null, "Traded Volume": 424608.0, "Turnover": 5246523.5, "Last Price of the Day": null, "Daily Traded Units": null, "Daily Turnover": null}, "1": {"Open": 12.29, "High": 12.29, "Low": 11.99, "Close": 12.09, "Change": null, "Traded Volume": 329050.0, "Turnover": 3978372.75, "Last Price of the Day": null, "Daily Traded Units": null, "Daily Turnover": null}, "2": {"Open": 11.92, "High": 11.92, "Low": 11.56, "Close": 11.64, "Change": null, "Traded Volume": 470424.0, "Turnover": 5496692.5, "Last Price of the Day": null, "Daily Traded Units": null, "Daily Turnover": null}, "3": {"Open": 11.7, "High": 12.07, "Low": 11.49, "Close": 11.52, "Change": null, "Traded Volume": 521879.0, "Turnover": 6123702.0, "Last Price of the Day": null, "Daily Traded Units": null, "Daily Turnover": null}, "4": {"Open": 11.59, "High": 11.6, "Low": 11.3, "Close": 11.6, "Change": null, "Traded Volume": 506541.0, "Turnover": 5798964.0, "Last Price of the Day": null, "Daily Traded Units": null, "Daily Turnover": null}, "5": {"Open": 12.0, "High": 12.2, "Low": 11.91, "Close": 11.93, "Change": null, "Traded Volume": 449437.0, "Turnover": 5399372.5, "Last Price of the Day": null, "Daily Traded Units": null, "Daily Turnover": null}, "6": {"Open": 12.13, "High": 12.24, "Low": 12.01, "Close": 12.14, "Change": null, "Traded Volume": 330523.0, "Turnover": 4009219.5, "Last Price of the Day": null, "Daily Traded Units": null, "Daily Turnover": null}, "7": {"Open": 12.1, "High": 12.15, "Low": 11.87, "Close": 11.92, "Change": null, "Traded Volume": 252866.0, "Turnover": 3030415.25, "Last Price of the Day": null, "Daily Traded Units": null, "Daily Turnover": null}, "8": {"Open": 11.9, "High": 12.14, "Low": 11.78, "Close": 12.06, "Change": null, "Traded Volume": 248628.0, "Turnover": 2978376.5, "Last Price of the Day": null, "Daily Traded Units": null, "Daily Turnover": null}, "9": {"Open": 12.0, "High": 12.48, "Low": 12.0, "Close": 12.24, "Change": null, "Traded Volume": 393800.0, "Turnover": 4837049.0, "Last Price of the Day": null, "Daily Traded Units": null, "Daily Turnover": null}, "10": {"Open": 12.4, "High": 12.58, "Low": 12.3, "Close": 12.51, "Change": null, "Traded Volume": 393223.0, "Turnover": 4899731.0, "Last Price of the Day": null, "Daily Traded Units": null, "Daily Turnover": null}, "11": {"Open": 12.6, "High": 12.77, "Low": 12.48, "Close": 12.53, "Change": null, "Traded Volume": 312797.0, "Turnover": 3951442.25, "Last Price of the Day": null, "Daily Traded Units": null, "Daily Turnover": null}, "12": {"Open": 12.46, "High": 12.66, "Low": 12.46, "Close": 12.55, "Change": null, "Traded Volume": 238184.0, "Turnover": 2996679.0, "Last Price of the Day": null, "Daily Traded Units": null, "Daily Turnover": null}, "13": {"Open": 12.7, "High": 12.86, "Low": 12.46, "Close": 12.47, "Change": null, "Traded Volume": 392867.0, "Turnover": 4955668.5, "Last Price of the Day": null, "Daily Traded Units": null, "Daily Turnover": null}, "14": {"Open": 12.5, "High": 12.56, "Low": 12.27, "Close": 12.41, "Change": null, "Traded Volume": 163599.0, "Turnover": 2028373.75, "Last Price of the Day": null, "Daily Traded Units": null, "Daily Turnover": null}, "15": {"Open": 12.23, "High": 12.25, "Low": 11.76, "Close": 12.1, "Change": null, "Traded Volume": 450413.0, "Turnover": 5416110.5, "Last Price of the Day": null, "Daily Traded Units": null, "Daily Turnover": null}, "16": {"Open": 12.24, "High": 12.55, "Low": 12.21, "Close": 12.51, "Change": null, "Traded Volume": 384516.0, "Turnover": 4767813.5, "Last Price of the Day": null, "Daily Traded Units": null, "Daily Turnover": null}, "17": {"Open": 12.4, "High": 12.54, "Low": 12.33, "Close": 12.52, "Change": null, "Traded Volume": 347917.0, "Turnover": 4337546.0, "Last Price of the Day": null, "Daily Traded Units": null, "Daily Turnover": null}, "18": {"Open": 12.55, "High": 12.9, "Low": 12.49, "Close": 12.8, "Change": null, "Traded Volume": 934725.0, "Turnover": 11943445.0, "Last Price of the Day": null, "Daily Traded Units": null, "Daily Turnover": null}, "19": {"Open": 12.72, "High": 12.84, "Low": 12.48, "Close": 12.63, "Change": null, "Traded Volume": 408791.0, "Turnover": 5186310.5, "Last Price of the Day": null, "Daily Traded Units": null, "Daily Turnover": null}, "20": {"Open": 12.39, "High": 12.5, "Low": 11.86, "Close": 11.89, "Change": null, "Traded Volume": 1371847.0, "Turnover": 16501375.0, "Last Price of the Day": null, "Daily Traded Units": null, "Daily Turnover": null}, "21": {"Open": 11.94, "High": 12.22, "Low": 11.75, "Close": 11.79, "Change": null, "Traded Volume": 563254.0, "Turnover": 6713097.5, "Last Price of the Day": null, "Daily Traded Units": null, "Daily Turnover": null}, "22": {"Open": 11.78, "High": 11.93, "Low": 11.65, "Close": 11.72, "Change": null, "Traded Volume": 255467.0, "Turnover": 3006317.0, "Last Price of the Day": null, "Daily Traded Units": null, "Daily Turnover": null}, "23": {"Open": 11.7, "High": 12.02, "Low": 11.7, "Close": 11.93, "Change": null, "Traded Volume": 360649.0, "Turnover": 4296136.0, "Last Price of the Day": null, "Daily Traded Units": null, "Daily Turnover": null}, "24": {"Open": 11.93, "High": 12.1, "Low": 11.91, "Close": 12.02, "Change": null, "Traded Volume": 837763.0, "Turnover": 10030524.0, "Last Price of the Day": null, "Daily Traded Units": null, "Daily Turnover": null}, "25": {"Open": 12.1, "High": 12.22, "Low": 11.84, "Close": 12.18, "Change": null, "Traded Volume": 450481.0, "Turnover": 5420938.5, "Last Price of the Day": null, "Daily Traded Units": null, "Daily Turnover": null}, "26": {"Open": 12.13, "High": 12.29, "Low": 11.96, "Close": 12.0, "Change": null, "Traded Volume": 282921.0, "Turnover": 3424974.25, "Last Price of the Day": null, "Daily Traded Units": null, "Daily Turnover": null}, "27": {"Open": 12.08, "High": 12.16, "Low": 11.88, "Close": 12.01, "Change": null, "Traded Volume": 219991.0, "Turnover": 2642822.25, "Last Price of the Day": null, "Daily Traded Units": null, "Daily Turnover": null}, "28": {"Open": 11.95, "High": 12.19, "Low": 11.95, "Close": 12.15, "Change": null, "Traded Volume": 280552.0, "Turnover": 3400709.0, "Last Price of the Day": null, "Daily Traded Units": null, "Daily Turnover": null}, "29": {"Open": 12.16, "High": 12.53, "Low": 12.05, "Close": 12.09, "Change": null, "Traded Volume": 718724.0, "Turnover": 8853306.0, "Last Price of the Day": null, "Daily Traded Units": null, "Daily Turnover": null}, "30": {"Open": 12.1, "High": 12.51, "Low": 12.1, "Close": 12.41, "Change": null, "Traded Volume": 830518.0, "Turnover": 10247839.0, "Last Price of the Day": null, "Daily Traded Units": null, "Daily Turnover": null}, "31": {"Open": 12.45, "High": 12.55, "Low": 12.41, "Close": 12.47, "Change": null, "Traded Volume": 453359.0, "Turnover": 5653389.0, "Last Price of the Day": null, "Daily Traded Units": null, "Daily Turnover": null}, "32": {"Open": 12.41, "High": 12.53, "Low": 12.37, "Close": 12.42, "Change": null, "Traded Volume": 187041.0, "Turnover": 2327272.5, "Last Price of the Day": null, "Daily Traded Units": null, "Daily Turnover": null}, "33": {"Open": 12.3, "High": 12.34, "Low": 12.04, "Close": 12.06, "Change": null, "Traded Volume": 257816.0, "Turnover": 3133551.5, "Last Price of the Day": null, "Daily Traded Units": null, "Daily Turnover": null}, "34": {"Open": 12.18, "High": 12.21, "Low": 11.9, "Close": 11.97, "Change": null, "Traded Volume": 417789.0, "Turnover": 5010536.5, "Last Price of the Day": null, "Daily Traded Units": null, "Daily Turnover": null}, "35": {"Open": 12.14, "High": 12.19, "Low": 11.92, "Close": 11.92, "Change": null, "Traded Volume": 410766.0, "Turnover": 4942888.5, "Last Price of the Day": null, "Daily Traded Units": null, "Daily Turnover": null}, "36": {"Open": 11.94, "High": 11.98, "Low": 11.68, "Close": 11.92, "Change": null, "Traded Volume": 456958.0, "Turnover": 5412489.5, "Last Price of the Day": null, "Daily Traded Units": null, "Daily Turnover": null}, "37": {"Open": 11.53, "High": 11.53, "Low": 10.9, "Close": 11.24, "Change": null, "Traded Volume": 1225484.0, "Turnover": 13678058.32, "Last Price of the Day": null, "Daily Traded Units": null, "Daily Turnover": null}, "38": {"Open": 11.21, "High": 11.34, "Low": 11.11, "Close": 11.23, "Change": null, "Traded Volume": 622848.0, "Turnover": 6997350.15, "Last Price of the Day": null, "Daily Traded Units": null, "Daily Turnover": null}, "39": {"Open": 10.9, "High": 11.46, "Low": 10.8, "Close": 11.45, "Change": null, "Traded Volume": 893504.0, "Turnover": 10002117.42, "Last Price of the Day": null, "Daily Traded Units": null, "Daily Turnover": null}, "40": {"Open": 11.25, "High": 11.35, "Low": 10.77, "Close": 10.9, "Change": null, "Traded Volume": 714196.0, "Turnover": 7899461.85, "Last Price of the Day": null, "Daily Traded Units": null, "Daily Turnover": null}, "41": {"Open": 10.45, "High": 10.67, "Low": 10.16, "Close": 10.63, "Change": null, "Traded Volume": 998844.0, "Turnover": 10458836.06, "Last Price of the Day": null, "Daily Traded Units": null, "Daily Turnover": null}, "42": {"Open": 10.7, "High": 10.94, "Low": 10.28, "Close": 10.57, "Change": null, "Traded Volume": 495238.0, "Turnover": 5231004.91, "Last Price of the Day": null, "Daily Traded Units": null, "Daily Turnover": null}, "43": {"Open": 10.94, "High": 11.23, "Low": 10.8, "Close": 10.97, "Change": null, "Traded Volume": 463353.0, "Turnover": 5121633.0, "Last Price of the Day": null, "Daily Traded Units": null, "Daily Turnover": null}, "44": {"Open": 11.04, "High": 11.22, "Low": 10.9, "Close": 11.03, "Change": null, "Traded Volume": 444802.0, "Turnover": 4912793.35, "Last Price of the Day": null, "Daily Traded Units": null, "Daily Turnover": null}, "45": {"Open": 11.15, "High": 11.24, "Low": 10.46, "Close": 10.6, "Change": null, "Traded Volume": 279669.0, "Turnover": 2983028.46, "Last Price of the Day": null, "Daily Traded Units": null, "Daily Turnover": null}, "46": {"Open": 10.42, "High": 10.5, "Low": 9.99, "Close": 10.5, "Change": null, "Traded Volume": 730959.0, "Turnover": 7527846.91, "Last Price of the Day": null, "Daily Traded Units": null, "Daily Turnover": null}, "47": {"Open": 9.26, "High": 9.8, "Low": 8.92, "Close": 8.99, "Change": null, "Traded Volume": 1217654.0, "Turnover": 11281362.32, "Last Price of the Day": null, "Daily Traded Units": null, "Daily Turnover": null}, "48": {"Open": 9.12, "High": 9.45, "Low": 8.765, "Close": 8.84, "Change": null, "Traded Volume": 857624.0, "Turnover": 7798645.33, "Last Price of the Day": null, "Daily Traded Units": null, "Daily Turnover": null}, "49": {"Open": 9.1, "High": 9.17, "Low": 8.245, "Close": 8.34, "Change": null, "Traded Volume": 1032000.0, "Turnover": 8869032.61, "Last Price of the Day": null, "Daily Traded Units": null, "Daily Turnover": null}, "50": {"Open": 7.8, "High": 7.85, "Low": 7.205, "Close": 7.29, "Change": null, "Traded Volume": 1072815.0, "Turnover": 8037186.33, "Last Price of the Day": null, "Daily Traded Units": null, "Daily Turnover": null}, "51": {"Open": 7.6, "High": 8.13, "Low": 7.18, "Close": 7.47, "Change": null, "Traded Volume": 726400.0, "Turnover": 5544296.99, "Last Price of the Day": null, "Daily Traded Units": null, "Daily Turnover": null}, "52": {"Open": 7.1, "High": 7.1, "Low": 6.135, "Close": 6.8, "Change": null, "Traded Volume": 1098595.0, "Turnover": 7235387.16, "Last Price of the Day": null, "Daily Traded Units": null, "Daily Turnover": null}, "53": {"Open": 7.0, "High": 7.19, "Low": 6.43, "Close": 7.125, "Change": null, "Traded Volume": 714175.0, "Turnover": 4863463.89, "Last Price of the Day": null, "Daily Traded Units": null, "Daily Turnover": null}, "54": {"Open": 6.87, "High": 6.87, "Low": 6.35, "Close": 6.35, "Change": null, "Traded Volume": 676042.0, "Turnover": 4377580.47, "Last Price of the Day": null, "Daily Traded Units": null, "Daily Turnover": null}, "55": {"Open": 6.155, "High": 6.48, "Low": 5.845, "Close": 6.025, "Change": null, "Traded Volume": 893099.0, "Turnover": 5423034.35, "Last Price of the Day": null, "Daily Traded Units": null, "Daily Turnover": null}, "56": {"Open": 6.51, "High": 6.52, "Low": 5.995, "Close": 6.035, "Change": null, "Traded Volume": 725589.0, "Turnover": 4528387.74, "Last Price of the Day": null, "Daily Traded Units": null, "Daily Turnover": null}, "57": {"Open": 5.97, "High": 6.08, "Low": 5.55, "Close": 5.66, "Change": null, "Traded Volume": 745693.0, "Turnover": 4309398.76, "Last Price of the Day": null, "Daily Traded Units": null, "Daily Turnover": null}, "58": {"Open": 6.59, "High": 7.895, "Low": 6.42, "Close": 7.545, "Change": null, "Traded Volume": 1816767.0, "Turnover": 13014970.49, "Last Price of the Day": null, "Daily Traded Units": null, "Daily Turnover": null}, "59": {"Open": 8.435, "High": 8.465, "Low": 7.595, "Close": 7.74, "Change": null, "Traded Volume": 1462195.0, "Turnover": 11670059.78, "Last Price of the Day": null, "Daily Traded Units": null, "Daily Turnover": null}, "60": {"Open": 7.6, "High": 7.7, "Low": 7.35, "Close": 7.505, "Change": null, "Traded Volume": 570942.0, "Turnover": 4294561.1, "Last Price of the Day": null, "Daily Traded Units": null, "Daily Turnover": null}, "61": {"Open": 7.595, "High": 7.625, "Low": 6.885, "Close": 7.04, "Change": null, "Traded Volume": 732318.0, "Turnover": 5263501.08, "Last Price of the Day": null, "Daily Traded Units": null, "Daily Turnover": null}, "62": {"Open": 7.02, "High": 7.58, "Low": 6.43, "Close": 7.255, "Change": null, "Traded Volume": 1270315.0, "Turnover": 9010793.52, "Last Price of the Day": null, "Daily Traded Units": null, "Daily Turnover": null}, "63": {"Open": 7.615, "High": 7.79, "Low": 6.995, "Close": 7.1, "Change": null, "Traded Volume": 1056197.0, "Turnover": 7686662.59, "Last Price of the Day": null, "Daily Traded Units": null, "Daily Turnover": null}, "64": {"Open": 7.0, "High": 7.19, "Low": 6.815, "Close": 7.11, "Change": null, "Traded Volume": 370128.0, "Turnover": 2601582.07, "Last Price of the Day": null, "Daily Traded Units": null, "Daily Turnover": null}, "65": {"Open": 7.15, "High": 7.27, "Low": 6.99, "Close": 7.1, "Change": null, "Traded Volume": 381422.0, "Turnover": 2709737.61, "Last Price of the Day": null, "Daily Traded Units": null, "Daily Turnover": null}, "66": {"Open": 7.48, "High": 7.56, "Low": 7.24, "Close": 7.375, "Change": null, "Traded Volume": 580424.0, "Turnover": 4298507.0, "Last Price of the Day": null, "Daily Traded Units": null, "Daily Turnover": null}, "67": {"Open": 7.65, "High": 7.87, "Low": 7.395, "Close": 7.4, "Change": null, "Traded Volume": 662807.0, "Turnover": 4989143.69, "Last Price of the Day": null, "Daily Traded Units": null, "Daily Turnover": null}, "68": {"Open": 7.785, "High": 8.03, "Low": 7.605, "Close": 7.74, "Change": null, "Traded Volume": 594710.0, "Turnover": 4641877.7, "Last Price of the Day": null, "Daily Traded Units": null, "Daily Turnover": null}, "69": {"Open": 7.695, "High": 8.265, "Low": 7.695, "Close": 7.945, "Change": null, "Traded Volume": 784158.0, "Turnover": 6273525.48, "Last Price of the Day": null, "Daily Traded Units": null, "Daily Turnover": null}, "70": {"Open": 8.205, "High": 8.33, "Low": 7.955, "Close": 8.15, "Change": null, "Traded Volume": 663518.0, "Turnover": 5390285.46, "Last Price of the Day": null, "Daily Traded Units": null, "Daily Turnover": null}, "71": {"Open": 8.31, "High": 8.32, "Low": 7.9, "Close": 7.99, "Change": null, "Traded Volume": 861768.0, "Turnover": 6954225.76, "Last Price of the Day": null, "Daily Traded Units": null, "Daily Turnover": null}, "72": {"Open": 8.02, "High": 8.03, "Low": 7.395, "Close": 7.535, "Change": null, "Traded Volume": 711886.0, "Turnover": 5421815.87, "Last Price of the Day": null, "Daily Traded Units": null, "Daily Turnover": null}, "73": {"Open": 7.74, "High": 7.91, "Low": 7.34, "Close": 7.4, "Change": null, "Traded Volume": 663420.0, "Turnover": 4960152.76, "Last Price of the Day": null, "Daily Traded Units": null, "Daily Turnover": null}, "74": {"Open": 7.65, "High": 7.925, "Low": 7.425, "Close": 7.485, "Change": null, "Traded Volume": 2779948.0, "Turnover": 20892104.61, "Last Price of the Day": null, "Daily Traded Units": null, "Daily Turnover": null}, "75": {"Open": 7.61, "High": 7.74, "Low": 7.445, "Close": 7.635, "Change": null, "Traded Volume": 315189.0, "Turnover": 2398397.63, "Last Price of the Day": null, "Daily Traded Units": null, "Daily Turnover": null}, "76": {"Open": 7.45, "High": 7.545, "Low": 7.135, "Close": 7.135, "Change": null, "Traded Volume": 535880.0, "Turnover": 3891377.66, "Last Price of the Day": null, "Daily Traded Units": null, "Daily Turnover": null}, "77": {"Open": 7.19, "High": 7.38, "Low": 7.025, "Close": 7.265, "Change": null, "Traded Volume": 397038.0, "Turnover": 2868935.86, "Last Price of the Day": null, "Daily Traded Units": null, "Daily Turnover": null}, "78": {"Open": 7.325, "High": 7.355, "Low": 7.115, "Close": 7.185, "Change": null, "Traded Volume": 433638.0, "Turnover": 3120892.88, "Last Price of the Day": null, "Daily Traded Units": null, "Daily Turnover": null}, "79": {"Open": 7.11, "High": 7.165, "Low": 6.945, "Close": 6.975, "Change": null, "Traded Volume": 505251.0, "Turnover": 3551832.64, "Last Price of the Day": null, "Daily Traded Units": null, "Daily Turnover": null}, "80": {"Open": 7.25, "High": 7.415, "Low": 7.19, "Close": 7.275, "Change": null, "Traded Volume": 347124.0, "Turnover": 2531735.44, "Last Price of the Day": null, "Daily Traded Units": null, "Daily Turnover": null}, "81": {"Open": 7.5, "High": 7.5, "Low": 7.235, "Close": 7.37, "Change": null, "Traded Volume": 499649.0, "Turnover": 3668964.07, "Last Price of the Day": null, "Daily Traded Units": null, "Daily Turnover": null}, "82": {"Open": 7.415, "High": 7.63, "Low": 7.27, "Close": 7.525, "Change": null, "Traded Volume": 829224.0, "Turnover": 6230237.63, "Last Price of the Day": null, "Daily Traded Units": null, "Daily Turnover": null}, "83": {"Open": 7.73, "High": 7.785, "Low": 7.295, "Close": 7.395, "Change": null, "Traded Volume": 681872.0, "Turnover": 5083322.33, "Last Price of the Day": null, "Daily Traded Units": null, "Daily Turnover": null}, "84": {"Open": 7.14, "High": 7.47, "Low": 6.99, "Close": 7.415, "Change": null, "Traded Volume": 500697.0, "Turnover": 3667247.37, "Last Price of the Day": null, "Daily Traded Units": null, "Daily Turnover": null}, "85": {"Open": 7.565, "High": 7.795, "Low": 7.46, "Close": 7.69, "Change": null, "Traded Volume": 728563.0, "Turnover": 5562291.66, "Last Price of the Day": null, "Daily Traded Units": null, "Daily Turnover": null}, "86": {"Open": 7.66, "High": 7.815, "Low": 7.55, "Close": 7.635, "Change": null, "Traded Volume": 399573.0, "Turnover": 3076269.52, "Last Price of the Day": null, "Daily Traded Units": null, "Daily Turnover": null}, "87": {"Open": 7.685, "High": 7.685, "Low": 7.42, "Close": 7.455, "Change": null, "Traded Volume": 414737.0, "Turnover": 3112167.16, "Last Price of the Day": null, "Daily Traded Units": null, "Daily Turnover": null}, "88": {"Open": 7.585, "High": 7.595, "Low": 7.35, "Close": 7.585, "Change": null, "Traded Volume": 408126.0, "Turnover": 3065693.62, "Last Price of the Day": null, "Daily Traded Units": null, "Daily Turnover": null}}